dlt_source_personio/__init__.py
dlt_source_personio/personio_oauth2_client_credentials.py
dlt_source_personio/rest_client.py
dlt_source_personio/settings.py
dlt_source_personio/type_adapters.py
dlt_source_personio/model/.gitattributes
dlt_source_personio/model/__init__.py
dlt_source_personio/model/v1/__init__.py
dlt_source_personio/model/v1/auth.py
dlt_source_personio/model/v1/personnel.py
dlt_source_personio/model/v1/recruiting.py
dlt_source_personio/model/v2/__init__.py
dlt_source_personio/model/v2/auth.py
dlt_source_personio/model/v2/employment.py
dlt_source_personio/model/v2/errors.py
dlt_source_personio/model/v2/person.py
dlt_source_personio-0.0.3.dist-info/METADATA
dlt_source_personio-0.0.3.dist-info/WHEEL
dlt_source_personio-0.0.3.dist-info/licenses/LICENSE
dlt_source_personio-0.0.3.dist-info/RECORD
