Metadata-Version: 2.4
Name: dlt-source-personio
Version: 0.0.3
Summary: A DLT source for personio
Project-URL: Repository, https://github.com/planet-a-ventures/dlt-source-personio
Author: Planet A Ventures
Maintainer-email: Joscha Feth <joscha@planet-a.com>
License: MIT
License-File: LICENSE
Keywords: dlt,dlthub,personio,source
Classifier: Development Status :: 4 - Beta
Classifier: Intended Audience :: Developers
Classifier: License :: OSI Approved :: MIT License
Classifier: Operating System :: OS Independent
Classifier: Programming Language :: Python :: 3
Classifier: Programming Language :: Python :: 3.12
Requires-Python: >=3.12
Requires-Dist: dlt>=1.9.0
Requires-Dist: jmespath>=1.0.1
Requires-Dist: pydantic-extra-types>=2.10.3
